{
  "a_comp_cor_00": {
    "CumulativeVarianceExplained": 0.1288850309,
    "Mask": "combined",
    "Method": "aCompCor",
    "Retained": true,
    "SingularValue": 197.2441011159,
    "VarianceExplained": 0.1288850309
  },
  "a_comp_cor_01": {
    "CumulativeVarianceExplained": 0.1558032872,
    "Mask": "combined",
    "Method": "aCompCor",
    "Retained": true,
    "SingularValue": 90.141804136,
    "VarianceExplained": 0.0269182563
  },
  "a_comp_cor_02": {
    "CumulativeVarianceExplained": 0.179586239,
    "Mask": "combined",
    "Method": "aCompCor",
    "Retained": true,
    "SingularValue": 84.7296986402,
    "VarianceExplained": 0.0237829518
  },
  "a_comp_cor_03": {
    "CumulativeVarianceExplained": 0.1996027213,
    "Mask": "combined",
    "Method": "aCompCor",
    "Retained": true,
    "SingularValue": 77.7314309393,
    "VarianceExplained": 0.0200164823
  },
  "a_comp_cor_04": {
    "CumulativeVarianceExplained": 0.2181937514,
    "Mask": "combined",
    "Method": "aCompCor",
    "Retained": true,
    "SingularValue": 74.9125379043,
    "VarianceExplained": 0.0185910301
  },
  "a_comp_cor_05": {
    "CumulativeVarianceExplained": 0.2340801124,
    "Mask": "combined",
    "Method": "aCompCor",
    "Retained": true,
    "SingularValue": 69.2492377051,
    "VarianceExplained": 0.015886361
  },
  "a_comp_cor_06": {
    "CumulativeVarianceExplained": 0.2492328443,
    "Mask": "combined",
    "Method": "aCompCor",
    "Retained": true,
    "SingularValue": 67.6313806217,
    "VarianceExplained": 0.0151527319
  },
  "a_comp_cor_07": {
    "CumulativeVarianceExplained": 0.2632669175,
    "Mask": "combined",
    "Method": "aCompCor",
    "Retained": true,
    "SingularValue": 65.0870598211,
    "VarianceExplained": 0.0140340733
  },
  "a_comp_cor_08": {
    "CumulativeVarianceExplained": 0.2756106208,
    "Mask": "combined",
    "Method": "aCompCor",
    "Retained": true,
    "SingularValue": 61.0415453715,
    "VarianceExplained": 0.0123437032
  },
  "a_comp_cor_09": {
    "CumulativeVarianceExplained": 0.2863302897,
    "Mask": "combined",
    "Method": "aCompCor",
    "Retained": true,
    "SingularValue": 56.8844378628,
    "VarianceExplained": 0.010719669
  },
  "a_comp_cor_10": {
    "CumulativeVarianceExplained": 0.2968325154,
    "Mask": "combined",
    "Method": "aCompCor",
    "Retained": true,
    "SingularValue": 56.304545584,
    "VarianceExplained": 0.0105022257
  },
  "a_comp_cor_11": {
    "CumulativeVarianceExplained": 0.3068959146,
    "Mask": "combined",
    "Method": "aCompCor",
    "Retained": true,
    "SingularValue": 55.1156752928,
    "VarianceExplained": 0.0100633991
  },
  "a_comp_cor_12": {
    "CumulativeVarianceExplained": 0.3167554854,
    "Mask": "combined",
    "Method": "aCompCor",
    "Retained": true,
    "SingularValue": 54.5546520726,
    "VarianceExplained": 0.0098595709
  },
  "a_comp_cor_13": {
    "CumulativeVarianceExplained": 0.3264299464,
    "Mask": "combined",
    "Method": "aCompCor",
    "Retained": true,
    "SingularValue": 54.0401034029,
    "VarianceExplained": 0.0096744609
  },
  "a_comp_cor_14": {
    "CumulativeVarianceExplained": 0.3358551777,
    "Mask": "combined",
    "Method": "aCompCor",
    "Retained": true,
    "SingularValue": 53.3394819804,
    "VarianceExplained": 0.0094252314
  },
  "a_comp_cor_15": {
    "CumulativeVarianceExplained": 0.3450540182,
    "Mask": "combined",
    "Method": "aCompCor",
    "Retained": true,
    "SingularValue": 52.6949901267,
    "VarianceExplained": 0.0091988405
  },
  "a_comp_cor_16": {
    "CumulativeVarianceExplained": 0.3539310574,
    "Mask": "combined",
    "Method": "aCompCor",
    "Retained": true,
    "SingularValue": 51.7650755594,
    "VarianceExplained": 0.0088770392
  },
  "a_comp_cor_17": {
    "CumulativeVarianceExplained": 0.3626571072,
    "Mask": "combined",
    "Method": "aCompCor",
    "Retained": true,
    "SingularValue": 51.3229518696,
    "VarianceExplained": 0.0087260498
  },
  "a_comp_cor_18": {
    "CumulativeVarianceExplained": 0.3712063984,
    "Mask": "combined",
    "Method": "aCompCor",
    "Retained": true,
    "SingularValue": 50.8004826747,
    "VarianceExplained": 0.0085492912
  },
  "a_comp_cor_19": {
    "CumulativeVarianceExplained": 0.3796703022,
    "Mask": "combined",
    "Method": "aCompCor",
    "Retained": true,
    "SingularValue": 50.5461571794,
    "VarianceExplained": 0.0084639038
  },
  "a_comp_cor_20": {
    "CumulativeVarianceExplained": 0.3880030959,
    "Mask": "combined",
    "Method": "aCompCor",
    "Retained": true,
    "SingularValue": 50.1531365391,
    "VarianceExplained": 0.0083327937
  },
  "a_comp_cor_21": {
    "CumulativeVarianceExplained": 0.3962590235,
    "Mask": "combined",
    "Method": "aCompCor",
    "Retained": true,
    "SingularValue": 49.9212810733,
    "VarianceExplained": 0.0082559276
  },
  "a_comp_cor_22": {
    "CumulativeVarianceExplained": 0.4043604982,
    "Mask": "combined",
    "Method": "aCompCor",
    "Retained": true,
    "SingularValue": 49.4521098322,
    "VarianceExplained": 0.0081014747
  },
  "a_comp_cor_23": {
    "CumulativeVarianceExplained": 0.412316859,
    "Mask": "combined",
    "Method": "aCompCor",
    "Retained": true,
    "SingularValue": 49.0072144111,
    "VarianceExplained": 0.0079563608
  },
  "a_comp_cor_24": {
    "CumulativeVarianceExplained": 0.4202162807,
    "Mask": "combined",
    "Method": "aCompCor",
    "Retained": true,
    "SingularValue": 48.8315415249,
    "VarianceExplained": 0.0078994217
  },
  "a_comp_cor_25": {
    "CumulativeVarianceExplained": 0.4280333752,
    "Mask": "combined",
    "Method": "aCompCor",
    "Retained": true,
    "SingularValue": 48.576415335,
    "VarianceExplained": 0.0078170944
  },
  "a_comp_cor_26": {
    "CumulativeVarianceExplained": 0.4358219566,
    "Mask": "combined",
    "Method": "aCompCor",
    "Retained": true,
    "SingularValue": 48.4877425265,
    "VarianceExplained": 0.0077885814
  },
  "a_comp_cor_27": {
    "CumulativeVarianceExplained": 0.4434871352,
    "Mask": "combined",
    "Method": "aCompCor",
    "Retained": true,
    "SingularValue": 48.1020874086,
    "VarianceExplained": 0.0076651786
  },
  "a_comp_cor_28": {
    "CumulativeVarianceExplained": 0.4510598846,
    "Mask": "combined",
    "Method": "aCompCor",
    "Retained": true,
    "SingularValue": 47.811192693,
    "VarianceExplained": 0.0075727494
  },
  "a_comp_cor_29": {
    "CumulativeVarianceExplained": 0.4585530295,
    "Mask": "combined",
    "Method": "aCompCor",
    "Retained": true,
    "SingularValue": 47.5592337646,
    "VarianceExplained": 0.0074931449
  },
  "a_comp_cor_30": {
    "CumulativeVarianceExplained": 0.4659353509,
    "Mask": "combined",
    "Method": "aCompCor",
    "Retained": true,
    "SingularValue": 47.2062236447,
    "VarianceExplained": 0.0073823214
  },
  "a_comp_cor_31": {
    "CumulativeVarianceExplained": 0.4733067238,
    "Mask": "combined",
    "Method": "aCompCor",
    "Retained": true,
    "SingularValue": 47.1712051878,
    "VarianceExplained": 0.0073713728
  },
  "a_comp_cor_32": {
    "CumulativeVarianceExplained": 0.4806184031,
    "Mask": "combined",
    "Method": "aCompCor",
    "Retained": true,
    "SingularValue": 46.9798203084,
    "VarianceExplained": 0.0073116793
  },
  "a_comp_cor_33": {
    "CumulativeVarianceExplained": 0.4877617711,
    "Mask": "combined",
    "Method": "aCompCor",
    "Retained": true,
    "SingularValue": 46.4359460884,
    "VarianceExplained": 0.0071433681
  },
  "a_comp_cor_34": {
    "CumulativeVarianceExplained": 0.4948749374,
    "Mask": "combined",
    "Method": "aCompCor",
    "Retained": true,
    "SingularValue": 46.3376775847,
    "VarianceExplained": 0.0071131662
  },
  "a_comp_cor_35": {
    "CumulativeVarianceExplained": 0.5019298801,
    "Mask": "combined",
    "Method": "aCompCor",
    "Retained": true,
    "SingularValue": 46.1476437227,
    "VarianceExplained": 0.0070549428
  },
  "c_comp_cor_00": {
    "CumulativeVarianceExplained": 0.177107247,
    "Mask": "CSF",
    "Method": "aCompCor",
    "Retained": true,
    "SingularValue": 79.8889025684,
    "VarianceExplained": 0.177107247
  },
  "c_comp_cor_01": {
    "CumulativeVarianceExplained": 0.2516355494,
    "Mask": "CSF",
    "Method": "aCompCor",
    "Retained": true,
    "SingularValue": 51.8237580996,
    "VarianceExplained": 0.0745283024
  },
  "c_comp_cor_02": {
    "CumulativeVarianceExplained": 0.3204453476,
    "Mask": "CSF",
    "Method": "aCompCor",
    "Retained": true,
    "SingularValue": 49.7958822533,
    "VarianceExplained": 0.0688097982
  },
  "c_comp_cor_03": {
    "CumulativeVarianceExplained": 0.3731332216,
    "Mask": "CSF",
    "Method": "aCompCor",
    "Retained": true,
    "SingularValue": 43.5736184832,
    "VarianceExplained": 0.052687874
  },
  "c_comp_cor_04": {
    "CumulativeVarianceExplained": 0.4146946877,
    "Mask": "CSF",
    "Method": "aCompCor",
    "Retained": true,
    "SingularValue": 38.7002453735,
    "VarianceExplained": 0.0415614661
  },
  "c_comp_cor_05": {
    "CumulativeVarianceExplained": 0.4538355733,
    "Mask": "CSF",
    "Method": "aCompCor",
    "Retained": true,
    "SingularValue": 37.5563703468,
    "VarianceExplained": 0.0391408856
  },
  "c_comp_cor_06": {
    "CumulativeVarianceExplained": 0.4868403482,
    "Mask": "CSF",
    "Method": "aCompCor",
    "Retained": true,
    "SingularValue": 34.4871000364,
    "VarianceExplained": 0.0330047749
  },
  "c_comp_cor_07": {
    "CumulativeVarianceExplained": 0.5135212467,
    "Mask": "CSF",
    "Method": "aCompCor",
    "Retained": true,
    "SingularValue": 31.0076257666,
    "VarianceExplained": 0.0266808984
  },
  "dropped_0": {
    "CumulativeVarianceExplained": 0.4284306392,
    "Mask": "Edge",
    "Method": "EdgeRegressor",
    "Retained": false,
    "SingularValue": 147.9472060384,
    "VarianceExplained": 0.0078136716
  },
  "dropped_1": {
    "CumulativeVarianceExplained": 0.4358925964,
    "Mask": "Edge",
    "Method": "EdgeRegressor",
    "Retained": false,
    "SingularValue": 144.5791169412,
    "VarianceExplained": 0.0074619572
  },
  "dropped_10": {
    "CumulativeVarianceExplained": 0.4982332755,
    "Mask": "Edge",
    "Method": "EdgeRegressor",
    "Retained": false,
    "SingularValue": 133.9147072561,
    "VarianceExplained": 0.0064017421
  },
  "dropped_100": {
    "CumulativeVarianceExplained": 0.9161050824,
    "Mask": "Edge",
    "Method": "EdgeRegressor",
    "Retained": false,
    "SingularValue": 100.7913873566,
    "VarianceExplained": 0.0036265065
  },
  "dropped_101": {
    "CumulativeVarianceExplained": 0.9197127079,
    "Mask": "Edge",
    "Method": "EdgeRegressor",
    "Retained": false,
    "SingularValue": 100.5286647072,
    "VarianceExplained": 0.0036076255
  },
  "dropped_102": {
    "CumulativeVarianceExplained": 0.9233113098,
    "Mask": "Edge",
    "Method": "EdgeRegressor",
    "Retained": false,
    "SingularValue": 100.4028624556,
    "VarianceExplained": 0.0035986019
  },
  "dropped_103": {
    "CumulativeVarianceExplained": 0.9268856425,
    "Mask": "Edge",
    "Method": "EdgeRegressor",
    "Retained": false,
    "SingularValue": 100.0637265471,
    "VarianceExplained": 0.0035743326
  },
  "dropped_104": {
    "CumulativeVarianceExplained": 0.9304575067,
    "Mask": "Edge",
    "Method": "EdgeRegressor",
    "Retained": false,
    "SingularValue": 100.0291692861,
    "VarianceExplained": 0.0035718642
  },
  "dropped_105": {
    "CumulativeVarianceExplained": 0.9340051212,
    "Mask": "Edge",
    "Method": "EdgeRegressor",
    "Retained": false,
    "SingularValue": 99.6890377877,
    "VarianceExplained": 0.0035476145
  },
  "dropped_106": {
    "CumulativeVarianceExplained": 0.9375151228,
    "Mask": "Edge",
    "Method": "EdgeRegressor",
    "Retained": false,
    "SingularValue": 99.1591619331,
    "VarianceExplained": 0.0035100016
  },
  "dropped_107": {
    "CumulativeVarianceExplained": 0.9410198441,
    "Mask": "Edge",
    "Method": "EdgeRegressor",
    "Retained": false,
    "SingularValue": 99.0845485497,
    "VarianceExplained": 0.0035047213
  },
  "dropped_108": {
    "CumulativeVarianceExplained": 0.9444981635,
    "Mask": "Edge",
    "Method": "EdgeRegressor",
    "Retained": false,
    "SingularValue": 98.7106284234,
    "VarianceExplained": 0.0034783193
  },
  "dropped_109": {
    "CumulativeVarianceExplained": 0.9479525208,
    "Mask": "Edge",
    "Method": "EdgeRegressor",
    "Retained": false,
    "SingularValue": 98.3700336448,
    "VarianceExplained": 0.0034543573
  },
  "dropped_11": {
    "CumulativeVarianceExplained": 0.5044862489,
    "Mask": "Edge",
    "Method": "EdgeRegressor",
    "Retained": false,
    "SingularValue": 132.3495531975,
    "VarianceExplained": 0.0062529734
  },
  "dropped_110": {
    "CumulativeVarianceExplained": 0.951403847,
    "Mask": "Edge",
    "Method": "EdgeRegressor",
    "Retained": false,
    "SingularValue": 98.326865255,
    "VarianceExplained": 0.0034513262
  },
  "dropped_111": {
    "CumulativeVarianceExplained": 0.9548346392,
    "Mask": "Edge",
    "Method": "EdgeRegressor",
    "Retained": false,
    "SingularValue": 98.0339261828,
    "VarianceExplained": 0.0034307922
  },
  "dropped_112": {
    "CumulativeVarianceExplained": 0.9582463895,
    "Mask": "Edge",
    "Method": "EdgeRegressor",
    "Retained": false,
    "SingularValue": 97.76148947,
    "VarianceExplained": 0.0034117503
  },
  "dropped_113": {
    "CumulativeVarianceExplained": 0.961646518,
    "Mask": "Edge",
    "Method": "EdgeRegressor",
    "Retained": false,
    "SingularValue": 97.5948395846,
    "VarianceExplained": 0.0034001285
  },
  "dropped_114": {
    "CumulativeVarianceExplained": 0.9650431348,
    "Mask": "Edge",
    "Method": "EdgeRegressor",
    "Retained": false,
    "SingularValue": 97.5444293592,
    "VarianceExplained": 0.0033966169
  },
  "dropped_115": {
    "CumulativeVarianceExplained": 0.9684030964,
    "Mask": "Edge",
    "Method": "EdgeRegressor",
    "Retained": false,
    "SingularValue": 97.0166652835,
    "VarianceExplained": 0.0033599615
  },
  "dropped_116": {
    "CumulativeVarianceExplained": 0.9717595116,
    "Mask": "Edge",
    "Method": "EdgeRegressor",
    "Retained": false,
    "SingularValue": 96.9654536226,
    "VarianceExplained": 0.0033564153
  },
  "dropped_117": {
    "CumulativeVarianceExplained": 0.9750867804,
    "Mask": "Edge",
    "Method": "EdgeRegressor",
    "Retained": false,
    "SingularValue": 96.5435215981,
    "VarianceExplained": 0.0033272688
  },
  "dropped_118": {
    "CumulativeVarianceExplained": 0.9783538642,
    "Mask": "Edge",
    "Method": "EdgeRegressor",
    "Retained": false,
    "SingularValue": 95.6663762487,
    "VarianceExplained": 0.0032670837
  },
  "dropped_119": {
    "CumulativeVarianceExplained": 0.98161028,
    "Mask": "Edge",
    "Method": "EdgeRegressor",
    "Retained": false,
    "SingularValue": 95.5100600795,
    "VarianceExplained": 0.0032564158
  },
  "dropped_12": {
    "CumulativeVarianceExplained": 0.5107006048,
    "Mask": "Edge",
    "Method": "EdgeRegressor",
    "Retained": false,
    "SingularValue": 131.9402348347,
    "VarianceExplained": 0.0062143559
  },
  "dropped_120": {
    "CumulativeVarianceExplained": 0.9848350548,
    "Mask": "Edge",
    "Method": "EdgeRegressor",
    "Retained": false,
    "SingularValue": 95.0449148633,
    "VarianceExplained": 0.0032247748
  },
  "dropped_121": {
    "CumulativeVarianceExplained": 0.988056826,
    "Mask": "Edge",
    "Method": "EdgeRegressor",
    "Retained": false,
    "SingularValue": 95.0006409432,
    "VarianceExplained": 0.0032217712
  },
  "dropped_122": {
    "CumulativeVarianceExplained": 0.9912645474,
    "Mask": "Edge",
    "Method": "EdgeRegressor",
    "Retained": false,
    "SingularValue": 94.7932721251,
    "VarianceExplained": 0.0032077215
  },
  "dropped_123": {
    "CumulativeVarianceExplained": 0.9944268231,
    "Mask": "Edge",
    "Method": "EdgeRegressor",
    "Retained": false,
    "SingularValue": 94.1193798568,
    "VarianceExplained": 0.0031622757
  },
  "dropped_124": {
    "CumulativeVarianceExplained": 0.9975587005,
    "Mask": "Edge",
    "Method": "EdgeRegressor",
    "Retained": false,
    "SingularValue": 93.6659111006,
    "VarianceExplained": 0.0031318773
  },
  "dropped_125": {
    "CumulativeVarianceExplained": 1.0,
    "Mask": "Edge",
    "Method": "EdgeRegressor",
    "Retained": false,
    "SingularValue": 82.6969943529,
    "VarianceExplained": 0.0024412995
  },
  "dropped_126": {
    "CumulativeVarianceExplained": 1.0,
    "Mask": "Edge",
    "Method": "EdgeRegressor",
    "Retained": false,
    "SingularValue": 0.0,
    "VarianceExplained": 0.0
  },
  "dropped_127": {
    "CumulativeVarianceExplained": 1.0,
    "Mask": "Edge",
    "Method": "EdgeRegressor",
    "Retained": false,
    "SingularValue": 0.0,
    "VarianceExplained": 0.0
  },
  "dropped_128": {
    "CumulativeVarianceExplained": 1.0,
    "Mask": "Edge",
    "Method": "EdgeRegressor",
    "Retained": false,
    "SingularValue": 0.0,
    "VarianceExplained": 0.0
  },
  "dropped_129": {
    "CumulativeVarianceExplained": 1.0,
    "Mask": "Edge",
    "Method": "EdgeRegressor",
    "Retained": false,
    "SingularValue": 0.0,
    "VarianceExplained": 0.0
  },
  "dropped_13": {
    "CumulativeVarianceExplained": 0.5168828262,
    "Mask": "Edge",
    "Method": "EdgeRegressor",
    "Retained": false,
    "SingularValue": 131.5986603206,
    "VarianceExplained": 0.0061822214
  },
  "dropped_130": {
    "CumulativeVarianceExplained": 1.0,
    "Mask": "Edge",
    "Method": "EdgeRegressor",
    "Retained": false,
    "SingularValue": 0.0,
    "VarianceExplained": 0.0
  },
  "dropped_131": {
    "CumulativeVarianceExplained": 1.0,
    "Mask": "Edge",
    "Method": "EdgeRegressor",
    "Retained": false,
    "SingularValue": 0.0,
    "VarianceExplained": 0.0
  },
  "dropped_14": {
    "CumulativeVarianceExplained": 0.5229257643,
    "Mask": "Edge",
    "Method": "EdgeRegressor",
    "Retained": false,
    "SingularValue": 130.1077780879,
    "VarianceExplained": 0.006042938
  },
  "dropped_15": {
    "CumulativeVarianceExplained": 0.528866268,
    "Mask": "Edge",
    "Method": "EdgeRegressor",
    "Retained": false,
    "SingularValue": 129.0003315415,
    "VarianceExplained": 0.0059405037
  },
  "dropped_16": {
    "CumulativeVarianceExplained": 0.5347068874,
    "Mask": "Edge",
    "Method": "EdgeRegressor",
    "Retained": false,
    "SingularValue": 127.9112211912,
    "VarianceExplained": 0.0058406194
  },
  "dropped_17": {
    "CumulativeVarianceExplained": 0.540484297,
    "Mask": "Edge",
    "Method": "EdgeRegressor",
    "Retained": false,
    "SingularValue": 127.2171816335,
    "VarianceExplained": 0.0057774096
  },
  "dropped_18": {
    "CumulativeVarianceExplained": 0.5462441905,
    "Mask": "Edge",
    "Method": "EdgeRegressor",
    "Retained": false,
    "SingularValue": 127.0241845191,
    "VarianceExplained": 0.0057598935
  },
  "dropped_19": {
    "CumulativeVarianceExplained": 0.5519325262,
    "Mask": "Edge",
    "Method": "EdgeRegressor",
    "Retained": false,
    "SingularValue": 126.2326794196,
    "VarianceExplained": 0.0056883357
  },
  "dropped_2": {
    "CumulativeVarianceExplained": 0.4433281002,
    "Mask": "Edge",
    "Method": "EdgeRegressor",
    "Retained": false,
    "SingularValue": 144.3226148893,
    "VarianceExplained": 0.0074355037
  },
  "dropped_20": {
    "CumulativeVarianceExplained": 0.5575804982,
    "Mask": "Edge",
    "Method": "EdgeRegressor",
    "Retained": false,
    "SingularValue": 125.784016059,
    "VarianceExplained": 0.005647972
  },
  "dropped_21": {
    "CumulativeVarianceExplained": 0.5631900248,
    "Mask": "Edge",
    "Method": "EdgeRegressor",
    "Retained": false,
    "SingularValue": 125.3551836337,
    "VarianceExplained": 0.0056095266
  },
  "dropped_22": {
    "CumulativeVarianceExplained": 0.5687359732,
    "Mask": "Edge",
    "Method": "EdgeRegressor",
    "Retained": false,
    "SingularValue": 124.6427733075,
    "VarianceExplained": 0.0055459484
  },
  "dropped_23": {
    "CumulativeVarianceExplained": 0.5742245846,
    "Mask": "Edge",
    "Method": "EdgeRegressor",
    "Retained": false,
    "SingularValue": 123.9967864809,
    "VarianceExplained": 0.0054886113
  },
  "dropped_24": {
    "CumulativeVarianceExplained": 0.5796659985,
    "Mask": "Edge",
    "Method": "EdgeRegressor",
    "Retained": false,
    "SingularValue": 123.4625022149,
    "VarianceExplained": 0.005441414
  },
  "dropped_25": {
    "CumulativeVarianceExplained": 0.5850862939,
    "Mask": "Edge",
    "Method": "EdgeRegressor",
    "Retained": false,
    "SingularValue": 123.2226850371,
    "VarianceExplained": 0.0054202954
  },
  "dropped_26": {
    "CumulativeVarianceExplained": 0.5904486873,
    "Mask": "Edge",
    "Method": "EdgeRegressor",
    "Retained": false,
    "SingularValue": 122.562757927,
    "VarianceExplained": 0.0053623934
  },
  "dropped_27": {
    "CumulativeVarianceExplained": 0.5957676323,
    "Mask": "Edge",
    "Method": "EdgeRegressor",
    "Retained": false,
    "SingularValue": 122.065220245,
    "VarianceExplained": 0.005318945
  },
  "dropped_28": {
    "CumulativeVarianceExplained": 0.6010745653,
    "Mask": "Edge",
    "Method": "EdgeRegressor",
    "Retained": false,
    "SingularValue": 121.9273101849,
    "VarianceExplained": 0.005306933
  },
  "dropped_29": {
    "CumulativeVarianceExplained": 0.6063464573,
    "Mask": "Edge",
    "Method": "EdgeRegressor",
    "Retained": false,
    "SingularValue": 121.524108566,
    "VarianceExplained": 0.005271892
  },
  "dropped_3": {
    "CumulativeVarianceExplained": 0.4506503464,
    "Mask": "Edge",
    "Method": "EdgeRegressor",
    "Retained": false,
    "SingularValue": 143.2192371471,
    "VarianceExplained": 0.0073222463
  },
  "dropped_30": {
    "CumulativeVarianceExplained": 0.6115644579,
    "Mask": "Edge",
    "Method": "EdgeRegressor",
    "Retained": false,
    "SingularValue": 120.9013781839,
    "VarianceExplained": 0.0052180006
  },
  "dropped_31": {
    "CumulativeVarianceExplained": 0.6167412579,
    "Mask": "Edge",
    "Method": "EdgeRegressor",
    "Retained": false,
    "SingularValue": 120.4231233399,
    "VarianceExplained": 0.0051768001
  },
  "dropped_32": {
    "CumulativeVarianceExplained": 0.6218913617,
    "Mask": "Edge",
    "Method": "EdgeRegressor",
    "Retained": false,
    "SingularValue": 120.1122158685,
    "VarianceExplained": 0.0051501037
  },
  "dropped_33": {
    "CumulativeVarianceExplained": 0.627000152,
    "Mask": "Edge",
    "Method": "EdgeRegressor",
    "Retained": false,
    "SingularValue": 119.629484172,
    "VarianceExplained": 0.0051087903
  },
  "dropped_34": {
    "CumulativeVarianceExplained": 0.6320796374,
    "Mask": "Edge",
    "Method": "EdgeRegressor",
    "Retained": false,
    "SingularValue": 119.2858829798,
    "VarianceExplained": 0.0050794854
  },
  "dropped_35": {
    "CumulativeVarianceExplained": 0.6371505893,
    "Mask": "Edge",
    "Method": "EdgeRegressor",
    "Retained": false,
    "SingularValue": 119.1856410813,
    "VarianceExplained": 0.0050709519
  },
  "dropped_36": {
    "CumulativeVarianceExplained": 0.6422020235,
    "Mask": "Edge",
    "Method": "EdgeRegressor",
    "Retained": false,
    "SingularValue": 118.956051266,
    "VarianceExplained": 0.0050514342
  },
  "dropped_37": {
    "CumulativeVarianceExplained": 0.6472256483,
    "Mask": "Edge",
    "Method": "EdgeRegressor",
    "Retained": false,
    "SingularValue": 118.6281585635,
    "VarianceExplained": 0.0050236248
  },
  "dropped_38": {
    "CumulativeVarianceExplained": 0.6522155834,
    "Mask": "Edge",
    "Method": "EdgeRegressor",
    "Retained": false,
    "SingularValue": 118.2297130658,
    "VarianceExplained": 0.004989935
  },
  "dropped_39": {
    "CumulativeVarianceExplained": 0.6571926512,
    "Mask": "Edge",
    "Method": "EdgeRegressor",
    "Retained": false,
    "SingularValue": 118.0771801745,
    "VarianceExplained": 0.0049770679
  },
  "dropped_4": {
    "CumulativeVarianceExplained": 0.4577162117,
    "Mask": "Edge",
    "Method": "EdgeRegressor",
    "Retained": false,
    "SingularValue": 140.6895583287,
    "VarianceExplained": 0.0070658653
  },
  "dropped_40": {
    "CumulativeVarianceExplained": 0.6621607466,
    "Mask": "Edge",
    "Method": "EdgeRegressor",
    "Retained": false,
    "SingularValue": 117.9706992756,
    "VarianceExplained": 0.0049680954
  },
  "dropped_41": {
    "CumulativeVarianceExplained": 0.667043998,
    "Mask": "Edge",
    "Method": "EdgeRegressor",
    "Retained": false,
    "SingularValue": 116.9590225934,
    "VarianceExplained": 0.0048832514
  },
  "dropped_42": {
    "CumulativeVarianceExplained": 0.6719072214,
    "Mask": "Edge",
    "Method": "EdgeRegressor",
    "Retained": false,
    "SingularValue": 116.7189302944,
    "VarianceExplained": 0.0048632234
  },
  "dropped_43": {
    "CumulativeVarianceExplained": 0.676761539,
    "Mask": "Edge",
    "Method": "EdgeRegressor",
    "Retained": false,
    "SingularValue": 116.6120110924,
    "VarianceExplained": 0.0048543176
  },
  "dropped_44": {
    "CumulativeVarianceExplained": 0.6816096433,
    "Mask": "Edge",
    "Method": "EdgeRegressor",
    "Retained": false,
    "SingularValue": 116.5373575498,
    "VarianceExplained": 0.0048481043
  },
  "dropped_45": {
    "CumulativeVarianceExplained": 0.6864241068,
    "Mask": "Edge",
    "Method": "EdgeRegressor",
    "Retained": false,
    "SingularValue": 116.1323308526,
    "VarianceExplained": 0.0048144636
  },
  "dropped_46": {
    "CumulativeVarianceExplained": 0.6912280576,
    "Mask": "Edge",
    "Method": "EdgeRegressor",
    "Retained": false,
    "SingularValue": 116.0054688073,
    "VarianceExplained": 0.0048039507
  },
  "dropped_47": {
    "CumulativeVarianceExplained": 0.6959991356,
    "Mask": "Edge",
    "Method": "EdgeRegressor",
    "Retained": false,
    "SingularValue": 115.6078840354,
    "VarianceExplained": 0.0047710781
  },
  "dropped_48": {
    "CumulativeVarianceExplained": 0.7007221785,
    "Mask": "Edge",
    "Method": "EdgeRegressor",
    "Retained": false,
    "SingularValue": 115.0244413539,
    "VarianceExplained": 0.0047230428
  },
  "dropped_49": {
    "CumulativeVarianceExplained": 0.7054315754,
    "Mask": "Edge",
    "Method": "EdgeRegressor",
    "Retained": false,
    "SingularValue": 114.8581550711,
    "VarianceExplained": 0.0047093969
  },
  "dropped_5": {
    "CumulativeVarianceExplained": 0.4647311703,
    "Mask": "Edge",
    "Method": "EdgeRegressor",
    "Retained": false,
    "SingularValue": 140.1818369234,
    "VarianceExplained": 0.0070149586
  },
  "dropped_50": {
    "CumulativeVarianceExplained": 0.7101211329,
    "Mask": "Edge",
    "Method": "EdgeRegressor",
    "Retained": false,
    "SingularValue": 114.6159671964,
    "VarianceExplained": 0.0046895575
  },
  "dropped_51": {
    "CumulativeVarianceExplained": 0.7147901229,
    "Mask": "Edge",
    "Method": "EdgeRegressor",
    "Retained": false,
    "SingularValue": 114.3643489335,
    "VarianceExplained": 0.00466899
  },
  "dropped_52": {
    "CumulativeVarianceExplained": 0.719439712,
    "Mask": "Edge",
    "Method": "EdgeRegressor",
    "Retained": false,
    "SingularValue": 114.1264952656,
    "VarianceExplained": 0.0046495892
  },
  "dropped_53": {
    "CumulativeVarianceExplained": 0.7240535037,
    "Mask": "Edge",
    "Method": "EdgeRegressor",
    "Retained": false,
    "SingularValue": 113.6863127973,
    "VarianceExplained": 0.0046137917
  },
  "dropped_54": {
    "CumulativeVarianceExplained": 0.7286632172,
    "Mask": "Edge",
    "Method": "EdgeRegressor",
    "Retained": false,
    "SingularValue": 113.6360579549,
    "VarianceExplained": 0.0046097135
  },
  "dropped_55": {
    "CumulativeVarianceExplained": 0.733221707,
    "Mask": "Edge",
    "Method": "EdgeRegressor",
    "Retained": false,
    "SingularValue": 113.0029243089,
    "VarianceExplained": 0.0045584898
  },
  "dropped_56": {
    "CumulativeVarianceExplained": 0.7377673731,
    "Mask": "Edge",
    "Method": "EdgeRegressor",
    "Retained": false,
    "SingularValue": 112.8438654262,
    "VarianceExplained": 0.0045456661
  },
  "dropped_57": {
    "CumulativeVarianceExplained": 0.7422860379,
    "Mask": "Edge",
    "Method": "EdgeRegressor",
    "Retained": false,
    "SingularValue": 112.5082210259,
    "VarianceExplained": 0.0045186649
  },
  "dropped_58": {
    "CumulativeVarianceExplained": 0.7467822784,
    "Mask": "Edge",
    "Method": "EdgeRegressor",
    "Retained": false,
    "SingularValue": 112.2287059127,
    "VarianceExplained": 0.0044962405
  },
  "dropped_59": {
    "CumulativeVarianceExplained": 0.7512662539,
    "Mask": "Edge",
    "Method": "EdgeRegressor",
    "Retained": false,
    "SingularValue": 112.0755311909,
    "VarianceExplained": 0.0044839755
  },
  "dropped_6": {
    "CumulativeVarianceExplained": 0.4716495488,
    "Mask": "Edge",
    "Method": "EdgeRegressor",
    "Retained": false,
    "SingularValue": 139.2134995751,
    "VarianceExplained": 0.0069183785
  },
  "dropped_60": {
    "CumulativeVarianceExplained": 0.75569276,
    "Mask": "Edge",
    "Method": "EdgeRegressor",
    "Retained": false,
    "SingularValue": 111.3550003751,
    "VarianceExplained": 0.0044265061
  },
  "dropped_61": {
    "CumulativeVarianceExplained": 0.7601126205,
    "Mask": "Edge",
    "Method": "EdgeRegressor",
    "Retained": false,
    "SingularValue": 111.2713794399,
    "VarianceExplained": 0.0044198605
  },
  "dropped_62": {
    "CumulativeVarianceExplained": 0.7645061856,
    "Mask": "Edge",
    "Method": "EdgeRegressor",
    "Retained": false,
    "SingularValue": 110.9398886112,
    "VarianceExplained": 0.0043935651
  },
  "dropped_63": {
    "CumulativeVarianceExplained": 0.7688971268,
    "Mask": "Edge",
    "Method": "EdgeRegressor",
    "Retained": false,
    "SingularValue": 110.9067547306,
    "VarianceExplained": 0.0043909411
  },
  "dropped_64": {
    "CumulativeVarianceExplained": 0.7732642716,
    "Mask": "Edge",
    "Method": "EdgeRegressor",
    "Retained": false,
    "SingularValue": 110.6058219743,
    "VarianceExplained": 0.0043671448
  },
  "dropped_65": {
    "CumulativeVarianceExplained": 0.7776056279,
    "Mask": "Edge",
    "Method": "EdgeRegressor",
    "Retained": false,
    "SingularValue": 110.2787676904,
    "VarianceExplained": 0.0043413563
  },
  "dropped_66": {
    "CumulativeVarianceExplained": 0.7819206032,
    "Mask": "Edge",
    "Method": "EdgeRegressor",
    "Retained": false,
    "SingularValue": 109.9431933588,
    "VarianceExplained": 0.0043149753
  },
  "dropped_67": {
    "CumulativeVarianceExplained": 0.7861917456,
    "Mask": "Edge",
    "Method": "EdgeRegressor",
    "Retained": false,
    "SingularValue": 109.3833490432,
    "VarianceExplained": 0.0042711424
  },
  "dropped_68": {
    "CumulativeVarianceExplained": 0.7904575938,
    "Mask": "Edge",
    "Method": "EdgeRegressor",
    "Retained": false,
    "SingularValue": 109.3155371004,
    "VarianceExplained": 0.0042658483
  },
  "dropped_69": {
    "CumulativeVarianceExplained": 0.7947110514,
    "Mask": "Edge",
    "Method": "EdgeRegressor",
    "Retained": false,
    "SingularValue": 109.1566611893,
    "VarianceExplained": 0.0042534576
  },
  "dropped_7": {
    "CumulativeVarianceExplained": 0.4784172508,
    "Mask": "Edge",
    "Method": "EdgeRegressor",
    "Retained": false,
    "SingularValue": 137.6891772111,
    "VarianceExplained": 0.006767702
  },
  "dropped_70": {
    "CumulativeVarianceExplained": 0.7989369256,
    "Mask": "Edge",
    "Method": "EdgeRegressor",
    "Retained": false,
    "SingularValue": 108.8021488134,
    "VarianceExplained": 0.0042258742
  },
  "dropped_71": {
    "CumulativeVarianceExplained": 0.8031579216,
    "Mask": "Edge",
    "Method": "EdgeRegressor",
    "Retained": false,
    "SingularValue": 108.7393311968,
    "VarianceExplained": 0.0042209959
  },
  "dropped_72": {
    "CumulativeVarianceExplained": 0.8073533528,
    "Mask": "Edge",
    "Method": "EdgeRegressor",
    "Retained": false,
    "SingularValue": 108.4095386122,
    "VarianceExplained": 0.0041954313
  },
  "dropped_73": {
    "CumulativeVarianceExplained": 0.8115219725,
    "Mask": "Edge",
    "Method": "EdgeRegressor",
    "Retained": false,
    "SingularValue": 108.0625792469,
    "VarianceExplained": 0.0041686197
  },
  "dropped_74": {
    "CumulativeVarianceExplained": 0.8156676619,
    "Mask": "Edge",
    "Method": "EdgeRegressor",
    "Retained": false,
    "SingularValue": 107.7649590951,
    "VarianceExplained": 0.0041456893
  },
  "dropped_75": {
    "CumulativeVarianceExplained": 0.8198043069,
    "Mask": "Edge",
    "Method": "EdgeRegressor",
    "Retained": false,
    "SingularValue": 107.6473438014,
    "VarianceExplained": 0.004136645
  },
  "dropped_76": {
    "CumulativeVarianceExplained": 0.8238979051,
    "Mask": "Edge",
    "Method": "EdgeRegressor",
    "Retained": false,
    "SingularValue": 107.0857777494,
    "VarianceExplained": 0.0040935982
  },
  "dropped_77": {
    "CumulativeVarianceExplained": 0.8279755297,
    "Mask": "Edge",
    "Method": "EdgeRegressor",
    "Retained": false,
    "SingularValue": 106.8766451208,
    "VarianceExplained": 0.0040776246
  },
  "dropped_78": {
    "CumulativeVarianceExplained": 0.8320377444,
    "Mask": "Edge",
    "Method": "EdgeRegressor",
    "Retained": false,
    "SingularValue": 106.6745028486,
    "VarianceExplained": 0.0040622147
  },
  "dropped_79": {
    "CumulativeVarianceExplained": 0.8360635832,
    "Mask": "Edge",
    "Method": "EdgeRegressor",
    "Retained": false,
    "SingularValue": 106.1958100534,
    "VarianceExplained": 0.0040258388
  },
  "dropped_8": {
    "CumulativeVarianceExplained": 0.4851679919,
    "Mask": "Edge",
    "Method": "EdgeRegressor",
    "Retained": false,
    "SingularValue": 137.5165331408,
    "VarianceExplained": 0.006750741
  },
  "dropped_80": {
    "CumulativeVarianceExplained": 0.8400675763,
    "Mask": "Edge",
    "Method": "EdgeRegressor",
    "Retained": false,
    "SingularValue": 105.9072880016,
    "VarianceExplained": 0.004003993
  },
  "dropped_81": {
    "CumulativeVarianceExplained": 0.8440590148,
    "Mask": "Edge",
    "Method": "EdgeRegressor",
    "Retained": false,
    "SingularValue": 105.7411215022,
    "VarianceExplained": 0.0039914385
  },
  "dropped_82": {
    "CumulativeVarianceExplained": 0.8480372049,
    "Mask": "Edge",
    "Method": "EdgeRegressor",
    "Retained": false,
    "SingularValue": 105.5654871384,
    "VarianceExplained": 0.0039781901
  },
  "dropped_83": {
    "CumulativeVarianceExplained": 0.8519807686,
    "Mask": "Edge",
    "Method": "EdgeRegressor",
    "Retained": false,
    "SingularValue": 105.1050596738,
    "VarianceExplained": 0.0039435637
  },
  "dropped_84": {
    "CumulativeVarianceExplained": 0.8559062578,
    "Mask": "Edge",
    "Method": "EdgeRegressor",
    "Retained": false,
    "SingularValue": 104.8639180395,
    "VarianceExplained": 0.0039254891
  },
  "dropped_85": {
    "CumulativeVarianceExplained": 0.8598017481,
    "Mask": "Edge",
    "Method": "EdgeRegressor",
    "Retained": false,
    "SingularValue": 104.4624615178,
    "VarianceExplained": 0.0038954903
  },
  "dropped_86": {
    "CumulativeVarianceExplained": 0.863691299,
    "Mask": "Edge",
    "Method": "EdgeRegressor",
    "Retained": false,
    "SingularValue": 104.3827948829,
    "VarianceExplained": 0.0038895509
  },
  "dropped_87": {
    "CumulativeVarianceExplained": 0.8675504735,
    "Mask": "Edge",
    "Method": "EdgeRegressor",
    "Retained": false,
    "SingularValue": 103.9743941133,
    "VarianceExplained": 0.0038591745
  },
  "dropped_88": {
    "CumulativeVarianceExplained": 0.8713992788,
    "Mask": "Edge",
    "Method": "EdgeRegressor",
    "Retained": false,
    "SingularValue": 103.834615843,
    "VarianceExplained": 0.0038488053
  },
  "dropped_89": {
    "CumulativeVarianceExplained": 0.8752278089,
    "Mask": "Edge",
    "Method": "EdgeRegressor",
    "Retained": false,
    "SingularValue": 103.5607596163,
    "VarianceExplained": 0.0038285302
  },
  "dropped_9": {
    "CumulativeVarianceExplained": 0.4918315335,
    "Mask": "Edge",
    "Method": "EdgeRegressor",
    "Retained": false,
    "SingularValue": 136.6254945591,
    "VarianceExplained": 0.0066635416
  },
  "dropped_90": {
    "CumulativeVarianceExplained": 0.8790220814,
    "Mask": "Edge",
    "Method": "EdgeRegressor",
    "Retained": false,
    "SingularValue": 103.0963876197,
    "VarianceExplained": 0.0037942725
  },
  "dropped_91": {
    "CumulativeVarianceExplained": 0.8828047127,
    "Mask": "Edge",
    "Method": "EdgeRegressor",
    "Retained": false,
    "SingularValue": 102.9381109351,
    "VarianceExplained": 0.0037826313
  },
  "dropped_92": {
    "CumulativeVarianceExplained": 0.886572575,
    "Mask": "Edge",
    "Method": "EdgeRegressor",
    "Retained": false,
    "SingularValue": 102.7369587111,
    "VarianceExplained": 0.0037678624
  },
  "dropped_93": {
    "CumulativeVarianceExplained": 0.8903280368,
    "Mask": "Edge",
    "Method": "EdgeRegressor",
    "Retained": false,
    "SingularValue": 102.5677587565,
    "VarianceExplained": 0.0037554618
  },
  "dropped_94": {
    "CumulativeVarianceExplained": 0.8940676441,
    "Mask": "Edge",
    "Method": "EdgeRegressor",
    "Retained": false,
    "SingularValue": 102.3510235121,
    "VarianceExplained": 0.0037396073
  },
  "dropped_95": {
    "CumulativeVarianceExplained": 0.8977850917,
    "Mask": "Edge",
    "Method": "EdgeRegressor",
    "Retained": false,
    "SingularValue": 102.0473234931,
    "VarianceExplained": 0.0037174476
  },
  "dropped_96": {
    "CumulativeVarianceExplained": 0.9014847308,
    "Mask": "Edge",
    "Method": "EdgeRegressor",
    "Retained": false,
    "SingularValue": 101.8025993057,
    "VarianceExplained": 0.003699639
  },
  "dropped_97": {
    "CumulativeVarianceExplained": 0.9051606613,
    "Mask": "Edge",
    "Method": "EdgeRegressor",
    "Retained": false,
    "SingularValue": 101.4758820467,
    "VarianceExplained": 0.0036759305
  },
  "dropped_98": {
    "CumulativeVarianceExplained": 0.9088323006,
    "Mask": "Edge",
    "Method": "EdgeRegressor",
    "Retained": false,
    "SingularValue": 101.4166352091,
    "VarianceExplained": 0.0036716393
  },
  "dropped_99": {
    "CumulativeVarianceExplained": 0.9124785759,
    "Mask": "Edge",
    "Method": "EdgeRegressor",
    "Retained": false,
    "SingularValue": 101.0657300058,
    "VarianceExplained": 0.0036462753
  },
  "edge_comp_00": {
    "CumulativeVarianceExplained": 0.0738221164,
    "Mask": "Edge",
    "Method": "EdgeRegressor",
    "Retained": true,
    "SingularValue": 454.749716,
    "VarianceExplained": 0.0738221164
  },
  "edge_comp_01": {
    "CumulativeVarianceExplained": 0.1104326929,
    "Mask": "Edge",
    "Method": "EdgeRegressor",
    "Retained": true,
    "SingularValue": 320.2450857966,
    "VarianceExplained": 0.0366105765
  },
  "edge_comp_02": {
    "CumulativeVarianceExplained": 0.1410823288,
    "Mask": "Edge",
    "Method": "EdgeRegressor",
    "Retained": true,
    "SingularValue": 293.0163473399,
    "VarianceExplained": 0.0306496359
  },
  "edge_comp_03": {
    "CumulativeVarianceExplained": 0.166395501,
    "Mask": "Edge",
    "Method": "EdgeRegressor",
    "Retained": true,
    "SingularValue": 266.2885405233,
    "VarianceExplained": 0.0253131722
  },
  "edge_comp_04": {
    "CumulativeVarianceExplained": 0.1897767545,
    "Mask": "Edge",
    "Method": "EdgeRegressor",
    "Retained": true,
    "SingularValue": 255.925220012,
    "VarianceExplained": 0.0233812534
  },
  "edge_comp_05": {
    "CumulativeVarianceExplained": 0.2106143528,
    "Mask": "Edge",
    "Method": "EdgeRegressor",
    "Retained": true,
    "SingularValue": 241.6033887584,
    "VarianceExplained": 0.0208375983
  },
  "edge_comp_06": {
    "CumulativeVarianceExplained": 0.231193017,
    "Mask": "Edge",
    "Method": "EdgeRegressor",
    "Retained": true,
    "SingularValue": 240.0975791082,
    "VarianceExplained": 0.0205786642
  },
  "edge_comp_07": {
    "CumulativeVarianceExplained": 0.2490520067,
    "Mask": "Edge",
    "Method": "EdgeRegressor",
    "Retained": true,
    "SingularValue": 223.6699467966,
    "VarianceExplained": 0.0178589897
  },
  "edge_comp_08": {
    "CumulativeVarianceExplained": 0.2649210997,
    "Mask": "Edge",
    "Method": "EdgeRegressor",
    "Retained": true,
    "SingularValue": 210.841085153,
    "VarianceExplained": 0.015869093
  },
  "edge_comp_09": {
    "CumulativeVarianceExplained": 0.2796352734,
    "Mask": "Edge",
    "Method": "EdgeRegressor",
    "Retained": true,
    "SingularValue": 203.023882847,
    "VarianceExplained": 0.0147141737
  },
  "edge_comp_10": {
    "CumulativeVarianceExplained": 0.2928128392,
    "Mask": "Edge",
    "Method": "EdgeRegressor",
    "Retained": true,
    "SingularValue": 192.1307094837,
    "VarianceExplained": 0.0131775658
  },
  "edge_comp_11": {
    "CumulativeVarianceExplained": 0.3053633261,
    "Mask": "Edge",
    "Method": "EdgeRegressor",
    "Retained": true,
    "SingularValue": 187.5035430742,
    "VarianceExplained": 0.0125504869
  },
  "edge_comp_12": {
    "CumulativeVarianceExplained": 0.3169527741,
    "Mask": "Edge",
    "Method": "EdgeRegressor",
    "Retained": true,
    "SingularValue": 180.1816529698,
    "VarianceExplained": 0.011589448
  },
  "edge_comp_13": {
    "CumulativeVarianceExplained": 0.3280507868,
    "Mask": "Edge",
    "Method": "EdgeRegressor",
    "Retained": true,
    "SingularValue": 176.320090201,
    "VarianceExplained": 0.0110980127
  },
  "edge_comp_14": {
    "CumulativeVarianceExplained": 0.3386246815,
    "Mask": "Edge",
    "Method": "EdgeRegressor",
    "Retained": true,
    "SingularValue": 172.106264994,
    "VarianceExplained": 0.0105738946
  },
  "edge_comp_15": {
    "CumulativeVarianceExplained": 0.3490069272,
    "Mask": "Edge",
    "Method": "EdgeRegressor",
    "Retained": true,
    "SingularValue": 170.5394439799,
    "VarianceExplained": 0.0103822457
  },
  "edge_comp_16": {
    "CumulativeVarianceExplained": 0.3592355575,
    "Mask": "Edge",
    "Method": "EdgeRegressor",
    "Retained": true,
    "SingularValue": 169.2730932456,
    "VarianceExplained": 0.0102286303
  },
  "edge_comp_17": {
    "CumulativeVarianceExplained": 0.3686663116,
    "Mask": "Edge",
    "Method": "EdgeRegressor",
    "Retained": true,
    "SingularValue": 162.5370611041,
    "VarianceExplained": 0.0094307542
  },
  "edge_comp_18": {
    "CumulativeVarianceExplained": 0.3780065229,
    "Mask": "Edge",
    "Method": "EdgeRegressor",
    "Retained": true,
    "SingularValue": 161.7549351584,
    "VarianceExplained": 0.0093402112
  },
  "edge_comp_19": {
    "CumulativeVarianceExplained": 0.3871335836,
    "Mask": "Edge",
    "Method": "EdgeRegressor",
    "Retained": true,
    "SingularValue": 159.8985999526,
    "VarianceExplained": 0.0091270608
  },
  "edge_comp_20": {
    "CumulativeVarianceExplained": 0.3961516795,
    "Mask": "Edge",
    "Method": "EdgeRegressor",
    "Retained": true,
    "SingularValue": 158.941246456,
    "VarianceExplained": 0.0090180959
  },
  "edge_comp_21": {
    "CumulativeVarianceExplained": 0.4044942949,
    "Mask": "Edge",
    "Method": "EdgeRegressor",
    "Retained": true,
    "SingularValue": 152.8728283361,
    "VarianceExplained": 0.0083426154
  },
  "edge_comp_22": {
    "CumulativeVarianceExplained": 0.4126572678,
    "Mask": "Edge",
    "Method": "EdgeRegressor",
    "Retained": true,
    "SingularValue": 151.2179580416,
    "VarianceExplained": 0.008162973
  },
  "edge_comp_23": {
    "CumulativeVarianceExplained": 0.4206169676,
    "Mask": "Edge",
    "Method": "EdgeRegressor",
    "Retained": true,
    "SingularValue": 149.3232842852,
    "VarianceExplained": 0.0079596997
  },
  "framewise_displacement": {
    "Units": "mm"
  },
  "rot_x": {
    "Description": "Rotation about left-right axis. Also known as \"pitch\".",
    "Units": "rad"
  },
  "rot_y": {
    "Description": "Rotation about anterior-posterior axis. Also known as \"roll\".",
    "Units": "rad"
  },
  "rot_z": {
    "Description": "Rotation about superior-inferior axis. Also known as \"yaw\".",
    "Units": "rad"
  },
  "t_comp_cor_00": {
    "CumulativeVarianceExplained": 0.2063846926,
    "Method": "tCompCor",
    "Retained": true,
    "SingularValue": 214.5700287117,
    "VarianceExplained": 0.2063846926
  },
  "t_comp_cor_01": {
    "CumulativeVarianceExplained": 0.3350216565,
    "Method": "tCompCor",
    "Retained": true,
    "SingularValue": 169.3999229828,
    "VarianceExplained": 0.1286369639
  },
  "t_comp_cor_02": {
    "CumulativeVarianceExplained": 0.4401299086,
    "Method": "tCompCor",
    "Retained": true,
    "SingularValue": 153.1259249318,
    "VarianceExplained": 0.1051082521
  },
  "t_comp_cor_03": {
    "CumulativeVarianceExplained": 0.5073788991,
    "Method": "tCompCor",
    "Retained": true,
    "SingularValue": 122.4822632167,
    "VarianceExplained": 0.0672489905
  },
  "trans_x": {
    "Description": "Translation along left-right axis.",
    "Units": "mm"
  },
  "trans_y": {
    "Description": "Translation along anterior-posterior axis.",
    "Units": "mm"
  },
  "trans_z": {
    "Description": "Translation along superior-inferior axis.",
    "Units": "mm"
  },
  "w_comp_cor_00": {
    "CumulativeVarianceExplained": 0.1292271438,
    "Mask": "WM",
    "Method": "aCompCor",
    "Retained": true,
    "SingularValue": 181.2173244538,
    "VarianceExplained": 0.1292271438
  },
  "w_comp_cor_01": {
    "CumulativeVarianceExplained": 0.1536067546,
    "Mask": "WM",
    "Method": "aCompCor",
    "Retained": true,
    "SingularValue": 78.7111442122,
    "VarianceExplained": 0.0243796108
  },
  "w_comp_cor_02": {
    "CumulativeVarianceExplained": 0.1746527736,
    "Mask": "WM",
    "Method": "aCompCor",
    "Retained": true,
    "SingularValue": 73.132062211,
    "VarianceExplained": 0.021046019
  },
  "w_comp_cor_03": {
    "CumulativeVarianceExplained": 0.1948405326,
    "Mask": "WM",
    "Method": "aCompCor",
    "Retained": true,
    "SingularValue": 71.6253731289,
    "VarianceExplained": 0.020187759
  },
  "w_comp_cor_04": {
    "CumulativeVarianceExplained": 0.2118745443,
    "Mask": "WM",
    "Method": "aCompCor",
    "Retained": true,
    "SingularValue": 65.7932457116,
    "VarianceExplained": 0.0170340117
  },
  "w_comp_cor_05": {
    "CumulativeVarianceExplained": 0.2271821517,
    "Mask": "WM",
    "Method": "aCompCor",
    "Retained": true,
    "SingularValue": 62.3701083974,
    "VarianceExplained": 0.0153076074
  },
  "w_comp_cor_06": {
    "CumulativeVarianceExplained": 0.2412380727,
    "Mask": "WM",
    "Method": "aCompCor",
    "Retained": true,
    "SingularValue": 59.765766821,
    "VarianceExplained": 0.0140559211
  },
  "w_comp_cor_07": {
    "CumulativeVarianceExplained": 0.2535247619,
    "Mask": "WM",
    "Method": "aCompCor",
    "Retained": true,
    "SingularValue": 55.8779259944,
    "VarianceExplained": 0.0122866892
  },
  "w_comp_cor_08": {
    "CumulativeVarianceExplained": 0.2656809775,
    "Mask": "WM",
    "Method": "aCompCor",
    "Retained": true,
    "SingularValue": 55.5804473197,
    "VarianceExplained": 0.0121562156
  },
  "w_comp_cor_09": {
    "CumulativeVarianceExplained": 0.2766992844,
    "Mask": "WM",
    "Method": "aCompCor",
    "Retained": true,
    "SingularValue": 52.9151794287,
    "VarianceExplained": 0.0110183069
  },
  "w_comp_cor_10": {
    "CumulativeVarianceExplained": 0.2875912095,
    "Mask": "WM",
    "Method": "aCompCor",
    "Retained": true,
    "SingularValue": 52.6108313063,
    "VarianceExplained": 0.0108919251
  },
  "w_comp_cor_11": {
    "CumulativeVarianceExplained": 0.2982758683,
    "Mask": "WM",
    "Method": "aCompCor",
    "Retained": true,
    "SingularValue": 52.1078519192,
    "VarianceExplained": 0.0106846588
  },
  "w_comp_cor_12": {
    "CumulativeVarianceExplained": 0.3081155205,
    "Mask": "WM",
    "Method": "aCompCor",
    "Retained": true,
    "SingularValue": 50.0049176226,
    "VarianceExplained": 0.0098396522
  },
  "w_comp_cor_13": {
    "CumulativeVarianceExplained": 0.3177374686,
    "Mask": "WM",
    "Method": "aCompCor",
    "Retained": true,
    "SingularValue": 49.448639296,
    "VarianceExplained": 0.0096219481
  },
  "w_comp_cor_14": {
    "CumulativeVarianceExplained": 0.3272577561,
    "Mask": "WM",
    "Method": "aCompCor",
    "Retained": true,
    "SingularValue": 49.1867212006,
    "VarianceExplained": 0.0095202875
  },
  "w_comp_cor_15": {
    "CumulativeVarianceExplained": 0.3365982769,
    "Mask": "WM",
    "Method": "aCompCor",
    "Retained": true,
    "SingularValue": 48.7201242998,
    "VarianceExplained": 0.0093405208
  },
  "w_comp_cor_16": {
    "CumulativeVarianceExplained": 0.3458059322,
    "Mask": "WM",
    "Method": "aCompCor",
    "Retained": true,
    "SingularValue": 48.3723702409,
    "VarianceExplained": 0.0092076553
  },
  "w_comp_cor_17": {
    "CumulativeVarianceExplained": 0.3547511242,
    "Mask": "WM",
    "Method": "aCompCor",
    "Retained": true,
    "SingularValue": 47.6779609452,
    "VarianceExplained": 0.008945192
  },
  "w_comp_cor_18": {
    "CumulativeVarianceExplained": 0.3636083527,
    "Mask": "WM",
    "Method": "aCompCor",
    "Retained": true,
    "SingularValue": 47.4429589433,
    "VarianceExplained": 0.0088572286
  },
  "w_comp_cor_19": {
    "CumulativeVarianceExplained": 0.37236639,
    "Mask": "WM",
    "Method": "aCompCor",
    "Retained": true,
    "SingularValue": 47.1765563647,
    "VarianceExplained": 0.0087580373
  },
  "w_comp_cor_20": {
    "CumulativeVarianceExplained": 0.3810129254,
    "Mask": "WM",
    "Method": "aCompCor",
    "Retained": true,
    "SingularValue": 46.875282878,
    "VarianceExplained": 0.0086465353
  },
  "w_comp_cor_21": {
    "CumulativeVarianceExplained": 0.3894736828,
    "Mask": "WM",
    "Method": "aCompCor",
    "Retained": true,
    "SingularValue": 46.3689715128,
    "VarianceExplained": 0.0084607574
  },
  "w_comp_cor_22": {
    "CumulativeVarianceExplained": 0.3978272096,
    "Mask": "WM",
    "Method": "aCompCor",
    "Retained": true,
    "SingularValue": 46.0741971814,
    "VarianceExplained": 0.0083535268
  },
  "w_comp_cor_23": {
    "CumulativeVarianceExplained": 0.4061563455,
    "Mask": "WM",
    "Method": "aCompCor",
    "Retained": true,
    "SingularValue": 46.0068835198,
    "VarianceExplained": 0.0083291359
  },
  "w_comp_cor_24": {
    "CumulativeVarianceExplained": 0.4143751532,
    "Mask": "WM",
    "Method": "aCompCor",
    "Retained": true,
    "SingularValue": 45.7011628591,
    "VarianceExplained": 0.0082188077
  },
  "w_comp_cor_25": {
    "CumulativeVarianceExplained": 0.4225478637,
    "Mask": "WM",
    "Method": "aCompCor",
    "Retained": true,
    "SingularValue": 45.5728196116,
    "VarianceExplained": 0.0081727105
  },
  "w_comp_cor_26": {
    "CumulativeVarianceExplained": 0.4305641681,
    "Mask": "WM",
    "Method": "aCompCor",
    "Retained": true,
    "SingularValue": 45.1346356744,
    "VarianceExplained": 0.0080163044
  },
  "w_comp_cor_27": {
    "CumulativeVarianceExplained": 0.4385099245,
    "Mask": "WM",
    "Method": "aCompCor",
    "Retained": true,
    "SingularValue": 44.9355917462,
    "VarianceExplained": 0.0079457564
  },
  "w_comp_cor_28": {
    "CumulativeVarianceExplained": 0.4464082994,
    "Mask": "WM",
    "Method": "aCompCor",
    "Retained": true,
    "SingularValue": 44.8014130275,
    "VarianceExplained": 0.0078983748
  },
  "w_comp_cor_29": {
    "CumulativeVarianceExplained": 0.4541611041,
    "Mask": "WM",
    "Method": "aCompCor",
    "Retained": true,
    "SingularValue": 44.386639369,
    "VarianceExplained": 0.0077528048
  },
  "w_comp_cor_30": {
    "CumulativeVarianceExplained": 0.4618588189,
    "Mask": "WM",
    "Method": "aCompCor",
    "Retained": true,
    "SingularValue": 44.2286566894,
    "VarianceExplained": 0.0076977148
  },
  "w_comp_cor_31": {
    "CumulativeVarianceExplained": 0.4694349049,
    "Mask": "WM",
    "Method": "aCompCor",
    "Retained": true,
    "SingularValue": 43.8778449614,
    "VarianceExplained": 0.007576086
  },
  "w_comp_cor_32": {
    "CumulativeVarianceExplained": 0.476927816,
    "Mask": "WM",
    "Method": "aCompCor",
    "Retained": true,
    "SingularValue": 43.6363214499,
    "VarianceExplained": 0.0074929111
  },
  "w_comp_cor_33": {
    "CumulativeVarianceExplained": 0.4843688634,
    "Mask": "WM",
    "Method": "aCompCor",
    "Retained": true,
    "SingularValue": 43.4850402854,
    "VarianceExplained": 0.0074410474
  },
  "w_comp_cor_34": {
    "CumulativeVarianceExplained": 0.491762999,
    "Mask": "WM",
    "Method": "aCompCor",
    "Retained": true,
    "SingularValue": 43.3477486916,
    "VarianceExplained": 0.0073941356
  },
  "w_comp_cor_35": {
    "CumulativeVarianceExplained": 0.4990374836,
    "Mask": "WM",
    "Method": "aCompCor",
    "Retained": true,
    "SingularValue": 42.9955942096,
    "VarianceExplained": 0.0072744846
  },
  "w_comp_cor_36": {
    "CumulativeVarianceExplained": 0.506241692,
    "Mask": "WM",
    "Method": "aCompCor",
    "Retained": true,
    "SingularValue": 42.7874076554,
    "VarianceExplained": 0.0072042084
  }
}